basicauth/__init__.py
basicauth/decorator.py
easy_basicauth-0.0.8.dist-info/LICENSE
easy_basicauth-0.0.8.dist-info/METADATA
easy_basicauth-0.0.8.dist-info/WHEEL
easy_basicauth-0.0.8.dist-info/top_level.txt
easy_basicauth-0.0.8.dist-info/RECORD
