Metadata-Version: 2.1
Name: easy-basicauth
Version: 0.0.8
Summary: Basic auth for Django
Home-page: https://github.com/bichanna/django-basic-auth
Author: bichanna
Author-email: nobu.bichanna@gmail.com
License: MIT
Keywords: basic-auth,python,django,api
Platform: UNKNOWN
Classifier: Framework :: Django
Classifier: Development Status :: 3 - Alpha
Classifier: Programming Language :: Python :: 3
License-File: LICENSE
Requires-Dist: django (>=1.8.0)
Requires-Dist: djangorestframework (>=3.0.0)
